{"mergeCondition":null,"minFlagCol":null,"format":"catalogTable","catalog":"chris_demos","path":"demos","insertInto":null,"provider":"delta","externalFilePath":"","mergeTargetAlias":"target","overwriteSchema":null,"enableSoftDelete":null,"flagValue":"integer","versionAsOf":null,"writeMode":"overwrite","description":"","replaceWhere":null,"historicColumns":[],"mergeSourceAlias":"source","filterQuery":"","notMatchedTable":[],"fromTimeCol":null,"notMatchedCondition":null,"matchedTable":[],"notMatchedAction":"insert","partitionColumns":null,"schema":{"type":"struct","fields":[{"name":"ingest_date","type":"date","nullable":true,"metadata":{"description":"","mappings":[],"tags":[]}},{"name":"ingest_ts","type":"timestamp","nullable":true,"metadata":{"description":"","mappings":[],"tags":[]}},{"name":"source_file","type":"string","nullable":true,"metadata":{"description":"","mappings":[],"tags":[]}},{"name":"row_in_file","type":"integer","nullable":true,"metadata":{"description":"","mappings":[],"tags":[]}},{"name":"event_id","type":"string","nullable":true,"metadata":{"description":"","mappings":[],"tags":[]}},{"name":"event_ts_raw","type":"string","nullable":true,"metadata":{"description":"","mappings":[],"tags":[]}},{"name":"order_id_raw","type":"string","nullable":true,"metadata":{"description":"","mappings":[],"tags":[]}},{"name":"customer_id_raw","type":"string","nullable":true,"metadata":{"description":"","mappings":[],"tags":[]}},{"name":"product_id_raw","type":"string","nullable":true,"metadata":{"description":"","mappings":[],"tags":[]}},{"name":"store_id_raw","type":"string","nullable":true,"metadata":{"description":"","mappings":[],"tags":[]}},{"name":"channel_raw","type":"string","nullable":true,"metadata":{"description":"","mappings":[],"tags":[]}},{"name":"country_raw","type":"string","nullable":true,"metadata":{"description":"","mappings":[],"tags":[]}},{"name":"city_raw","type":"string","nullable":true,"metadata":{"description":"","mappings":[],"tags":[]}},{"name":"quantity_raw","type":"string","nullable":true,"metadata":{"description":"","mappings":[],"tags":[]}},{"name":"unit_price_raw","type":"string","nullable":true,"metadata":{"description":"","mappings":[],"tags":[]}},{"name":"discount_pct_raw","type":"string","nullable":true,"metadata":{"description":"","mappings":[],"tags":[]}},{"name":"currency_raw","type":"string","nullable":false,"metadata":{"description":"","mappings":[],"tags":[]}},{"name":"payment_method_raw","type":"string","nullable":true,"metadata":{"description":"","mappings":[],"tags":[]}},{"name":"status_raw","type":"string","nullable":false,"metadata":{"description":"","mappings":[],"tags":[]}},{"name":"notes_raw","type":"string","nullable":true,"metadata":{"description":"","mappings":[],"tags":[]}},{"name":"raw_payload","type":"string","nullable":true,"metadata":{"description":"","mappings":[],"tags":[]}}]},"activeTab":"whenMatched","tableName":"silver_retail_events","maxFlagCol":null,"matchedConditionDelete":null,"isCatalogEnabled":true,"additionalProperties":{"copilot":{"datasetDescriptionStatus":"fromUser"}},"componentInfo":{"gemId":"gitUri=http://gitserver:3000/DxEheDCJ_team_5751/DxEheDCJ_project_12654.git&subPath=&tag=0.2.53&projectSubscriptionProjectId=12654&path=gems/catalogTable","projectName":"ProphecySparkBasicsPython"},"matchedActionDelete":"ignore","timestampAsOf":null,"mergeSchema":null,"toTimeCol":null,"optimizeWrite":null,"useExternalFilePath":false,"mergeSchemaEvolution":null,"keyColumns":[],"createMinMaxFlags":true,"matchedCondition":null,"matchedAction":"update","datasetType":"Database","fileFormat":"parquet"}